keras_fft/__init__.py
keras_fft/fft/__init__.py
keras_fft/fft/jax.py
keras_fft/fft/tensorflow.py
keras_fft/fft_derivative/__init__.py
keras_fft/fft_derivative/jax.py
keras_fft/fft_derivative/tensorflow.py
keras_fft/helper/jax.py
keras_fft/helper/tensorflow.py
keras_fft-1.0.0.dist-info/licenses/LICENSE
keras_fft-1.0.0.dist-info/METADATA
keras_fft-1.0.0.dist-info/WHEEL
keras_fft-1.0.0.dist-info/top_level.txt
keras_fft-1.0.0.dist-info/RECORD
