Metadata-Version: 2.4
Name: keras-fft
Version: 1.0.0
Summary: FFT pack for Keras3
Author-email: Mathies Wedler <mathies.wedler@gmail.com>
License-Expression: GPL-3.0-or-later
Project-URL: Homepage, https://github.com/MathiesW/KerasFFT
Project-URL: Source, https://github.com/MathiesW/KerasFFT
Classifier: Programming Language :: Python :: 3
Classifier: Operating System :: OS Independent
Requires-Python: >=3.8
License-File: LICENSE
Requires-Dist: keras
Provides-Extra: tensorflow
Requires-Dist: tensorflow; extra == "tensorflow"
Provides-Extra: jax
Requires-Dist: jax; extra == "jax"
Requires-Dist: jaxlib; extra == "jax"
Dynamic: license-file
